wgkex/__init__.py
wgkex/broker/__init__.py
wgkex/broker/app.py
wgkex/broker/templates/index.html
wgkex/config/__init__.py
wgkex/config/config.py
wgkex-0.1.0.dist-info/METADATA
wgkex-0.1.0.dist-info/WHEEL
wgkex-0.1.0.dist-info/top_level.txt
wgkex-0.1.0.dist-info/RECORD
