Metadata-Version: 2.1
Name: wgkex
Version: 0.1.0
Summary: WireGuard Key Exchange
Home-page: https://github.com/freifunkMUC/wgkex
Author: UNKNOWN
Author-email: UNKNOWN
License: UNKNOWN
Platform: UNKNOWN
Requires-Dist: Flask
Requires-Dist: PyYAML
Requires-Dist: voluptuous
